README.md
setup.py
EasyAdls/EasyAdls.py
EasyAdls/__init__.py
EasyAdls.egg-info/PKG-INFO
EasyAdls.egg-info/SOURCES.txt
EasyAdls.egg-info/dependency_links.txt
EasyAdls.egg-info/requires.txt
EasyAdls.egg-info/top_level.txt