Metadata-Version: 2.1
Name: EasyAdls
Version: 0.1.3
Summary: Wrapper around the Azure Storage Blobs SDK to make life a bit easier
Home-page: https://github.com/danielkoops1/easy_adls
Author: D. Koops
Requires-Python: >=3.6
